zapgpt/__init__.py
zapgpt/__main__.py
zapgpt/cli.py
zapgpt/config.py
zapgpt/default_pricing.json
zapgpt/main.py
zapgpt/prompts/coding.json
zapgpt/prompts/common_base.json
zapgpt/prompts/create_passwd.json
zapgpt/prompts/cyber_awareness.json
zapgpt/prompts/default.json
zapgpt/prompts/kali.json
zapgpt/prompts/linux_log_analysis.json
zapgpt/prompts/linuxrootquest.json
zapgpt/prompts/poml.json
zapgpt/prompts/powershell.json
zapgpt/prompts/prompting.json
zapgpt/prompts/python.json
zapgpt/prompts/re.json
zapgpt/prompts/theredtactician.json
zapgpt/prompts/vuln_assessment.json
zapgpt-3.4.19.dist-info/licenses/LICENSE
zapgpt-3.4.19.dist-info/METADATA
zapgpt-3.4.19.dist-info/WHEEL
zapgpt-3.4.19.dist-info/entry_points.txt
zapgpt-3.4.19.dist-info/top_level.txt
zapgpt-3.4.19.dist-info/RECORD
