Metadata-Version: 2.4
Name: zapgpt
Version: 3.4.19
Summary: A command-line tool for interacting with various LLM providers
Author-email: Amit Agarwal <amit@labnol.org>
Maintainer-email: Amit Agarwal <amit@example.com>
License: MIT License
Project-URL: Homepage, https://github.com/raj77in/zapgpt
Project-URL: Repository, https://github.com/raj77in/zapgpt
Project-URL: Issues, https://github.com/raj77in/zapgpt/issues
Project-URL: Documentation, https://github.com/raj77in/zapgpt#readme
Keywords: ai,llm,gpt,openai,anthropic,mistral,cli,chat,terminal
Classifier: Development Status :: 5 - Production/Stable
Classifier: Environment :: Console
Classifier: Intended Audience :: Developers
Classifier: Intended Audience :: End Users/Desktop
Classifier: Intended Audience :: System Administrators
Classifier: License :: OSI Approved :: MIT License
Classifier: Operating System :: OS Independent
Classifier: Programming Language :: Python :: 3
Classifier: Programming Language :: Python :: 3.9
Classifier: Programming Language :: Python :: 3.10
Classifier: Programming Language :: Python :: 3.11
Classifier: Programming Language :: Python :: 3.12
Classifier: Programming Language :: Python :: 3.13
Classifier: Topic :: Communications :: Chat
Classifier: Topic :: Internet :: WWW/HTTP :: Dynamic Content
Classifier: Topic :: Scientific/Engineering :: Artificial Intelligence
Classifier: Topic :: Software Development :: Libraries :: Python Modules
Classifier: Topic :: Terminals
Classifier: Topic :: Utilities
Requires-Python: >=3.9
License-File: LICENSE
Requires-Dist: openai>=1.54.0
Requires-Dist: requests>=2.32.3
Requires-Dist: tabulate>=0.9.0
Requires-Dist: tiktoken>=0.8.0
Requires-Dist: rich>=13.9.4
Requires-Dist: pygments>=2.18.0
Requires-Dist: httpx>=0.28.1
Requires-Dist: rich-argparse>=1.7.1
Requires-Dist: python-dotenv>=1.0.0
Requires-Dist: typing-extensions>=4.12.2
Requires-Dist: python-dateutil>=2.9.0
Requires-Dist: pydantic>=2.7.0
Requires-Dist: importlib-resources>=6.4.0; python_version < "3.9"
Requires-Dist: tomli>=2.0.0; python_version < "3.11"
Provides-Extra: dev
Requires-Dist: ruff>=0.1.0; extra == "dev"
Requires-Dist: mypy>=1.0; extra == "dev"
Requires-Dist: pre-commit>=3.0; extra == "dev"
Requires-Dist: pytest>=8.4.1; extra == "dev"
Requires-Dist: pytest-cov>=4.0; extra == "dev"
Requires-Dist: pytest-mock>=3.10; extra == "dev"
Provides-Extra: test
Requires-Dist: pytest>=8.4.1; extra == "test"
Requires-Dist: pytest-cov>=4.0; extra == "test"
Requires-Dist: pytest-mock>=3.10; extra == "test"
Dynamic: license-file
